<directory>
	<param>
		<name>Jaune-Rouge</name>
		<float>1.0</float>
		<float>1.0</float>
		<float>0.0</float>
		<float>1.0</float>
		<float>0.1</float>
		<float>0.1</float>
	</param>
	<param>
		<name>Rouge-Jaune</name>
		<float>1.0</float>
		<float>0.1</float>
		<float>0.1</float>
		<float>1.0</float>
		<float>1.0</float>
		<float>0.0</float>
	</param>
	<param>
		<name>Bleu-Rouge</name>
		<float>0.0</float>
		<float>0.0</float>
		<float>1.0</float>
		<float>1.0</float>
		<float>0.0</float>
		<float>0.0</float>
	</param>
	<param>
		<name>Rouge-Bleu</name>
		<float>1.0</float>
		<float>0.0</float>
		<float>0.0</float>
		<float>0.0</float>
		<float>0.0</float>
		<float>1.0</float>
	</param>
	<param>
		<name>Vert-Rouge</name>
		<float>0.0</float>
		<float>1.0</float>
		<float>0.0</float>
		<float>1.0</float>
		<float>0.0</float>
		<float>0.0</float>
	</param>
	<param>
		<name>Rouge-Vert</name>
		<float>1.0</float>
		<float>0.0</float>
		<float>0.0</float>
		<float>0.0</float>
		<float>1.0</float>
		<float>0.0</float>
	</param>
	<param>
		<name>Jaune-Vert</name>
		<float>1.0</float>
		<float>1.0</float>
		<float>0.0</float>
		<float>0.0</float>
		<float>1.0</float>
		<float>0.0</float>
	</param>
	<param>
		<name>Vert-Jaune</name>
		<float>0.0</float>
		<float>1.0</float>
		<float>0.0</float>
		<float>1.0</float>
		<float>1.0</float>
		<float>0.0</float>
	</param>
	<param>
		<name>Jaune-Bleu</name>
		<float>1.0</float>
		<float>1.0</float>
		<float>0.0</float>
		<float>0.0</float>
		<float>0.0</float>
		<float>1.0</float>
	</param>
	<param>
		<name>Bleu-Jaune</name>
		<float>0.0</float>
		<float>0.0</float>
		<float>1.0</float>
		<float>1.0</float>
		<float>1.0</float>
		<float>0.0</float>
	</param>
	<param>
		<name>Blanc-Bleu</name>
		<float>1.0</float>
		<float>1.0</float>
		<float>1.0</float>
		<float>0.0</float>
		<float>0.0</float>
		<float>1.0</float>
	</param>
	<param>
		<name>Bleu-Blanc</name>
		<float>0.0</float>
		<float>0.0</float>
		<float>1.0</float>
		<float>1.0</float>
		<float>1.0</float>
		<float>1.0</float>
	</param>
	<param>
		<name>Blanc-Vert</name>
		<float>1.0</float>
		<float>1.0</float>
		<float>1.0</float>
		<float>0.0</float>
		<float>1.0</float>
		<float>0.0</float>
	</param>
	<param>
		<name>Vert-Blanc</name>
		<float>0.0</float>
		<float>1.0</float>
		<float>0.0</float>
		<float>1.0</float>
		<float>1.0</float>
		<float>1.0</float>
	</param>
	<param>
		<name>Blanc-Noir</name>
		<float>1.0</float>
		<float>1.0</float>
		<float>1.0</float>
		<float>0.0</float>
		<float>0.0</float>
		<float>0.0</float>
	</param>
	<param>
		<name>Noir-Blanc</name>
		<float>0.0</float>
		<float>0.0</float>
		<float>0.0</float>
		<float>1.0</float>
		<float>1.0</float>
		<float>1.0</float>
	</param>
</directory>